citations_collector/__init__.py
citations_collector/_version.py
citations_collector/cli.py
citations_collector/core.py
citations_collector/merge_detection.py
citations_collector/pdf.py
citations_collector/py.typed
citations_collector/unpaywall.py
citations_collector/zotero_sync.py
citations_collector/discovery/__init__.py
citations_collector/discovery/base.py
citations_collector/discovery/crossref.py
citations_collector/discovery/datacite.py
citations_collector/discovery/openalex.py
citations_collector/discovery/opencitations.py
citations_collector/discovery/utils.py
citations_collector/importers/__init__.py
citations_collector/importers/bibtex.py
citations_collector/importers/dandi.py
citations_collector/importers/github.py
citations_collector/importers/zenodo.py
citations_collector/importers/zotero.py
citations_collector/models/__init__.py
citations_collector/models/generated.py
citations_collector/persistence/__init__.py
citations_collector/persistence/tsv_io.py
citations_collector/persistence/yaml_io.py
citations_collector-0.2.3.dist-info/METADATA
citations_collector-0.2.3.dist-info/WHEEL
citations_collector-0.2.3.dist-info/entry_points.txt
citations_collector-0.2.3.dist-info/RECORD
