Metadata-Version: 2.4
Name: citations-collector
Version: 0.2.3
Summary: Discover and curate scholarly citations of datasets and software
Project-URL: Homepage, https://github.com/dandi/citations-collector
Project-URL: Repository, https://github.com/dandi/citations-collector
Project-URL: Issues, https://github.com/dandi/citations-collector/issues
Author-email: DANDI <team@dandiarchive.org>
License: MIT
Classifier: Development Status :: 3 - Alpha
Classifier: Intended Audience :: Science/Research
Classifier: License :: OSI Approved :: MIT License
Classifier: Programming Language :: Python :: 3
Classifier: Programming Language :: Python :: 3.10
Classifier: Programming Language :: Python :: 3.11
Classifier: Programming Language :: Python :: 3.12
Classifier: Topic :: Scientific/Engineering
Requires-Python: >=3.10
Requires-Dist: bibtexparser>=2.0.0b7
Requires-Dist: click>=8.0
Requires-Dist: pydantic>=2.0
Requires-Dist: pyyaml>=6.0
Requires-Dist: pyzotero>=1.5
Requires-Dist: rapidfuzz>=3.0
Requires-Dist: requests>=2.28
Requires-Dist: tqdm>=4.0
Requires-Dist: urllib3>=1.26
Provides-Extra: ci
Requires-Dist: mypy>=1.0; extra == 'ci'
Requires-Dist: pre-commit>=3.0; extra == 'ci'
Requires-Dist: pytest-cov>=4.0; extra == 'ci'
Requires-Dist: pytest-timeout>=2.0; extra == 'ci'
Requires-Dist: pytest>=7.0; extra == 'ci'
Requires-Dist: responses>=0.23; extra == 'ci'
Requires-Dist: ruff>=0.1.0; extra == 'ci'
Requires-Dist: tox-gh-actions>=3.0; extra == 'ci'
Requires-Dist: tox-uv>=1.0; extra == 'ci'
Requires-Dist: tox>=4.0; extra == 'ci'
Requires-Dist: types-pyyaml; extra == 'ci'
Requires-Dist: types-requests; extra == 'ci'
Requires-Dist: types-tqdm; extra == 'ci'
Provides-Extra: dandi
Requires-Dist: dandi>=0.60.0; extra == 'dandi'
Provides-Extra: devel
Requires-Dist: mypy>=1.0; extra == 'devel'
Requires-Dist: pre-commit>=3.0; extra == 'devel'
Requires-Dist: pytest-cov>=4.0; extra == 'devel'
Requires-Dist: pytest-timeout>=2.0; extra == 'devel'
Requires-Dist: pytest>=7.0; extra == 'devel'
Requires-Dist: responses>=0.23; extra == 'devel'
Requires-Dist: ruff>=0.1.0; extra == 'devel'
Requires-Dist: tox-uv>=1.0; extra == 'devel'
Requires-Dist: tox>=4.0; extra == 'devel'
Requires-Dist: types-pyyaml; extra == 'devel'
Requires-Dist: types-requests; extra == 'devel'
Requires-Dist: types-tqdm; extra == 'devel'
Provides-Extra: linkml
Requires-Dist: linkml-runtime>=1.7.0; extra == 'linkml'
Requires-Dist: linkml>=1.7.0; extra == 'linkml'
Provides-Extra: test
Requires-Dist: pytest-cov>=4.0; extra == 'test'
Requires-Dist: pytest-timeout>=2.0; extra == 'test'
Requires-Dist: pytest>=7.0; extra == 'test'
Requires-Dist: responses>=0.23; extra == 'test'
